.DS_Store
torchKbert/__init__.py
torchKbert/__main__.py
torchKbert/convert_gpt2_checkpoint_to_pytorch.py
torchKbert/convert_openai_checkpoint_to_pytorch.py
torchKbert/convert_tf_checkpoint_to_pytorch.py
torchKbert/convert_transfo_xl_checkpoint_to_pytorch.py
torchKbert/file_utils.py
torchKbert/modeling.py
torchKbert/modeling_gpt2.py
torchKbert/modeling_openai.py
torchKbert/modeling_transfo_xl.py
torchKbert/modeling_transfo_xl_utilities.py
torchKbert/optimization.py
torchKbert/optimization_openai.py
torchKbert/tokenization.py
torchKbert/tokenization_gpt2.py
torchKbert/tokenization_openai.py
torchKbert/tokenization_transfo_xl.py
torchKbert-1.1.3.dist-info/LICENSE
torchKbert-1.1.3.dist-info/METADATA
torchKbert-1.1.3.dist-info/WHEEL
torchKbert-1.1.3.dist-info/entry_points.txt
torchKbert-1.1.3.dist-info/top_level.txt
torchKbert-1.1.3.dist-info/RECORD
