Metadata-Version: 2.1
Name: torchKbert
Version: 1.1.3
Summary: An customized pytorch version of pre-trained model.
Home-page: https://github.com/KKenny0/torchKbert
Author: KennyWu
Author-email: kennywu96@163.com
License: Apache
Keywords: BERT NLP deep learning
Platform: UNKNOWN
License-File: LICENSE
Requires-Dist: torch (>=0.4.1)
Requires-Dist: numpy
Requires-Dist: boto3
Requires-Dist: requests
Requires-Dist: tqdm
Requires-Dist: regex
